{
  "type": "FeatureCollection",
  "features": [
    {
      "type": "Feature",
      "properties": {
        "marker-color": "#7e7e7e",
        "marker-size": "medium",
        "marker-symbol": "city",
        "name": "Sydney"
      },
      "geometry": {
        "type": "Point",
        "coordinates": [
          151.21376037597656,
          -33.8521697014074
        ]
      }
    }
  ]
}